bmlab_toolkit/__init__.py
bmlab_toolkit/constants.py
bmlab_toolkit/erase_cli.py
bmlab_toolkit/flashing.py
bmlab_toolkit/jlink_programmer.py
bmlab_toolkit/programmer.py
bmlab_toolkit/rtt_cli.py
bmlab_toolkit/scan_cli.py
bmlab_toolkit-0.2.1.dist-info/licenses/LICENSE
bmlab_toolkit-0.2.1.dist-info/METADATA
bmlab_toolkit-0.2.1.dist-info/WHEEL
bmlab_toolkit-0.2.1.dist-info/entry_points.txt
bmlab_toolkit-0.2.1.dist-info/top_level.txt
bmlab_toolkit-0.2.1.dist-info/RECORD
