Metadata-Version: 2.4
Name: bmlab-toolkit
Version: 0.2.1
Summary: CI/CD toolkit for flashing and testing embedded devices
Author-email: BareMetal Test Lab <makloun@hotmail.com>
License: MIT
Project-URL: Homepage, https://github.com/BareMetalTestLab/bmlab-flash-toolkit
Project-URL: Repository, https://github.com/BareMetalTestLab/bmlab-flash-toolkit
Project-URL: Bug Tracker, https://github.com/BareMetalTestLab/bmlab-flash-toolkit/issues
Project-URL: Documentation, https://github.com/BareMetalTestLab/bmlab-flash-toolkit#readme
Keywords: embedded,firmware,flashing,jlink,stm32,ci-cd,testing
Classifier: Development Status :: 3 - Alpha
Classifier: Intended Audience :: Developers
Classifier: License :: OSI Approved :: MIT License
Classifier: Programming Language :: Python :: 3
Classifier: Programming Language :: Python :: 3.8
Classifier: Programming Language :: Python :: 3.9
Classifier: Programming Language :: Python :: 3.10
Classifier: Programming Language :: Python :: 3.11
Classifier: Programming Language :: Python :: 3.12
Requires-Python: >=3.8
License-File: LICENSE
Requires-Dist: pylink-square>=1.0.0
Provides-Extra: dev
Requires-Dist: pytest>=7.0; extra == "dev"
Requires-Dist: pytest-cov>=4.0; extra == "dev"
Dynamic: license-file
